main.py
source_looker/__init__.py
source_looker/components.py
source_looker/manifest.yaml
source_looker/run.py
source_looker/source.py
airbyte_source_looker-1.0.34.dist-info/METADATA
airbyte_source_looker-1.0.34.dist-info/WHEEL
airbyte_source_looker-1.0.34.dist-info/entry_points.txt
airbyte_source_looker-1.0.34.dist-info/RECORD
