Metadata-Version: 2.3
Name: airbyte-source-looker
Version: 1.0.34
Summary: Source implementation for looker.
License: MIT
Author: Airbyte
Author-email: contact@airbyte.io
Requires-Python: >=3.10,<4.0
Classifier: License :: OSI Approved :: MIT License
Classifier: Programming Language :: Python :: 3
Classifier: Programming Language :: Python :: 3.10
Classifier: Programming Language :: Python :: 3.11
Classifier: Programming Language :: Python :: 3.12
Classifier: Programming Language :: Python :: 3.13
Requires-Dist: airbyte-cdk (>=4.0.1,<5.0.0)
Requires-Dist: pytz (>=2024.1,<2025.0)
Project-URL: Documentation, https://docs.airbyte.com/integrations/sources/looker
Project-URL: Homepage, https://airbyte.com
Project-URL: Repository, https://github.com/airbytehq/airbyte
